client/__init__.py
client/helper.py
client/main.py
copier/__init__.py
copier/main.py
example/__init__.py
example/data.py
example/main.py
schema/__init__.py
schema/main.py
utility/__init__.py
utility/main.py
appsync_copier-0.0.3.dist-info/LICENSE
appsync_copier-0.0.3.dist-info/METADATA
appsync_copier-0.0.3.dist-info/WHEEL
appsync_copier-0.0.3.dist-info/top_level.txt
appsync_copier-0.0.3.dist-info/RECORD
